fichub_cli_metadata/__init__.py
fichub_cli_metadata/cli.py
fichub_cli_metadata/utils/__init__.py
fichub_cli_metadata/utils/crud.py
fichub_cli_metadata/utils/fetch_data.py
fichub_cli_metadata/utils/logging.py
fichub_cli_metadata/utils/models.py
fichub_cli_metadata/utils/processing.py
fichub_cli_metadata-0.6.6.dist-info/LICENSE.txt
fichub_cli_metadata-0.6.6.dist-info/METADATA
fichub_cli_metadata-0.6.6.dist-info/WHEEL
fichub_cli_metadata-0.6.6.dist-info/entry_points.txt
fichub_cli_metadata-0.6.6.dist-info/top_level.txt
fichub_cli_metadata-0.6.6.dist-info/RECORD
