Metadata-Version: 2.1
Name: fichub-cli-metadata
Version: 0.6.6
Summary: A metadata plugin for fetching Metadata from the Fichub API for the fichub-cli
Home-page: https://github.com/fichub-cli-contrib/fichub-cli-metadata
Author: Arbaaz Laskar
Author-email: arzkar.dev@gmail.com
License: Apache License
Classifier: Programming Language :: Python :: 3
Classifier: License :: OSI Approved :: Apache Software License
Classifier: Operating System :: OS Independent
License-File: LICENSE.txt
Requires-Dist: fichub-cli>=0.9.3
Requires-Dist: rich>=10.4.0
Requires-Dist: sqlalchemy>=1.4.31
